[
{
"Citation": "Psa 2:1.6",
"Current": "רִֽיק",
"Recommended": "רִ֥יק",
"Note": "There is a Merkha under Resh.",
"Folio": "366A",
"Column": 1,
"Line": 11
},
{
"Citation": "Psa 2:2.10",
"Current": "מְשִׁיחֽוֹ",
"Recommended": "מְשִׁיח֥וֹ",
"Note": "There appears to be a Merkha under Het.",
"Folio": "366A",
"Column": 1,
"Line": 13
},
{
"Citation": "Psa 3:4.7",
"Current": "רֹאשִֽׁי",
"Recommended": "רֹאשִׁ֥י",
"Note": "There appears to be a Merkha under Shin.",
"Folio": "366A",
"Column": 2,
"Line": 4
},
{
"Citation": "Psa 3:5.1",
"Current": "ק֭וֹלִי",
"Recommended": "ק֖וֹלִי",
"Note": "There is a Tarcha under Qof.",
"Folio": "366A",
"Column": 2,
"Line": 4
},
{
"Citation": "Psa 3:7.8",
"Current": "עָלָֽי",
"Recommended": "עָלָ֥י",
"Note": "There appears to be a Merkha under Lamed.",
"Folio": "366A",
"Column": 2,
"Line": 7
},
{
"Citation": "Psa 6:3.10",
"Current": "עֲצָמֽ͏ָי",
"Recommended": "עֲצָֽמָי",
"Note": "The Meteg appears more aligned beside the first Qamats.",
"Folio": "366B",
"Column": 1,
"Line": 16
},
{
"Citation": "Psa 8:3.10",
"Current": "וּמִתְנַקֵּֽם",
"Recommended": "וּמִתְנַקֵּ֥ם",
"Note": "There is a Merkha under Qof.",
"Folio": "366B",
"Column": 2,
"Line": 25
},
{
"Citation": "Psa 8:9.6",
"Current": "אָרְח֥וֹת",
"Recommended": "אָרְחֽוֹת",
"Note": "There is a Meteg under Het.",
"Folio": "367A",
"Column": 1,
"Line": 5
},
{
"Citation": "Psa 9:9.7",
"Current": "בְּמֵישָׁרִֽים",
"Recommended": "בְּמֵישָֽׁרִים",
"Note": "The Meteg appears to be under Shin.",
"Folio": "367A",
"Column": 1,
"Line": 16
},
{
"Citation": "Psa 10:10.4",
"Current": "בַּ֝עֲצוּמָ֗יו",
"Recommended": "בַּ֝עֲצוּמָּ֗יו",
"Note": "There appears to be a Dagesh in Mem.",
"Folio": "367A",
"Column": 2,
"Line": 19
},
{
"Citation": "Psa 13:2.11",
"Current": "מִמֶּֽנִּי",
"Recommended": "מִמֶּֽנִי",
"Note": "There is no Dagesh in Nun.",
"Folio": "367B",
"Column": 2,
"Line": 4
},
{
"Citation": "Psa 15:1.3",
"Current": "יְ֭הֹוָה",
"Recommended": "י֭הֹוָה",
"Note": "There is no Sheva under Yod.",
"Folio": "367B",
"Column": 2,
"Line": 25
},
{
"Citation": "Psa 15:2.7",
"Current": "בִּלְבָבֽוֹ",
"Recommended": "בִּלְבָֽבוֹ",
"Note": "The Meteg is under the second Bet.",
"Folio": "367B",
"Column": 2,
"Line": 27
},
{
"Citation": "Psa 17:14.12",
"Current": "יִשְׂבְּע֥וּ",
"Recommended": "יִשְׂבּ֥עוּ",
"Note": "There appears to be a Metheg under Bet.",
"Folio": "368A",
"Column": 2,
"Line": 15
},
{
"Citation": "Psa 17:14.16",
"Current": "לְעוֹלְלֵיהֽ͏ֶם",
"Recommended": "לְעוֹלְלֵֽיהֶם",
"Note": "The Meteg is under the third Lamed.",
"Folio": "368A",
"Column": 2,
"Line": 15
},
{
"Citation": "Psa 17:15.6",
"Current": "בְ֝הָקִ֗יץ",
"Recommended": "בְֿ֝הָקִ֗יץ",
"Note": "There appears to be a Rafe above Bet. [Perhaps just add a note rather than making a change.]",
"Folio": "368A",
"Column": 2,
"Line": 16
},
{
"Citation": "Psa 18:3.2",
"Current": "סַֽלְעִ֥י",
"Note": "It is common in L for Metheg and Merkha to look alike. The Aleppo is missing at this place, but the HaKeter and MAM both have a Merkha in both places.",
"Folio": "368A",
"Column": 2,
"Line": null
},
{
"Citation": "Psa 18:3.6",
"Current": "צ֭וּרִי",
"Recommended": "צ֖וּרִי",
"Note": "There appears to be a Tarcha under Tsadi.",
"Folio": "368A",
"Column": 2,
"Line": 23
},
{
"Citation": "Psa 18:7.3",
"Current": "אֶֽקְרָ֣א",
"Recommended": "אֶֽקֲרָ֣א",
"Note": "There is a Hataf Patah under Qof.",
"Folio": "368A",
"Column": 2,
"Line": 27
},
{
"Citation": "Psa 18:20.4",
"Current": "כִּ֘י",
"Recommended": "כִ֘י",
"Note": "There appears to be no Dagesh in Kaf. The below image shows the markings for this passage are very clear and the speck in Kaf is most likely a blemish.",
"Folio": "368B",
"Column": 1,
"Line": 17
 
},
{
"Citation": "Psa 19:15.1",
"Current": "יִֽהְי֥וּ",
"Recommended": "יִֽהְי֥וּ־",
"Note": "There appears to be a Maqaf after Shuruk.",
"Folio": "369A",
"Column": 1,
"Line": 18
},
{
"Citation": "Psa 25:3.3",
"Current": "קֹ֭וֶיךָ",
"Recommended": "ק֭וֹיֶךָ",
"Note": "The Segol is under Yod.",
"Folio": "370A",
"Column": 1,
"Line": 8
},
{
"Citation": "Psa 26:4.5",
"Current": "שָׁ֑וְא",
"Recommended": "שָׁ֑וא",
"Note": "Something was erased under the Vav.",
"Folio": "370A",
"Column": 2,
"Line": 8
},
{
"Citation": "Psa 28:1.8",
"Current": "מִ֫מֶּ֥נִּי",
"Recommended": "מִּ֫מֶּ֥נִּי",
"Note": "There appears to be a faded Dagesh in the first Mem.",
"Folio": "370B",
"Column": 1,
"Line": 15
},
{
"Citation": "Psa 28:7.11",
"Current": "אֲהוֹדֶֽנּוּ׃",
"Recommended": "אֲהוֹדֶנּוּ׃",
"Note": "There is no Silluq (Meteg under Dalet).",
"Folio": "370B",
"Column": 1,
"Line": 26
},
{
"Citation": "Psa 30:1.3",
"Current": "חֲנֻכַּ֖ת",
"Recommended": "חֲנֻכַּת",
"Note": "The large darkened diagonal mark under Kaf might be a Tarcha. [Perhaps just add a note rather than making a change.]",
"Folio": "370B",
"Column": 2,
"Line": 15
},
{
"Citation": "Psa 30:4.3",
"Current": "מִן־",
"Recommended": "מִּן־",
"Note": "There appears to be a Dagesh in Mem.",
"Folio": "370B",
"Column": 2,
"Line": 18
},
{
"Citation": "Psa 30:10.5",
"Current": "אֶ֫ל־",
"Recommended": "אֶ֫ל",
"Note": "There is no Maqaf at the end of the word.",
"Folio": "370B",
"Column": 2,
"Line": 25
},
{
"Citation": "Psa 31:5.8",
"Current": "מָֽעוּזִּֽי",
"Recommended": "מָֽעוּזִּי",
"Note": "There is no Meteg under Zayin.",
"Folio": "371A",
"Column": 1,
"Line": 10
},
{
"Citation": "Psa 31:7.4",
"Current": "שָׁ֑וְא",
"Recommended": "שָׁ֑וא",
"Note": "There is no Sheva under Vav",
"Folio": "371A",
"Column": 1,
"Line": 12
},
{
"Citation": "Psa 31:19.9",
"Current": "וָבֽוּז",
"Recommended": "וָבוּז",
"Note": "There is no Meteg under Bet. The mast and flag of the lower Lamed give the appearance of a superimposed Meteg. [See images providing] examples of mast and flag of Lamed that looks similar to this example.",
"Folio": "371A",
"Column": 2,
"Line": 3
},
{
"Citation": "Psa 32:3.3",
"Current": "בָּל֣וּ",
"Recommended": "בָּ֣לוּ",
"Note": "The Munah is positioned under Bet.",
"Folio": "371A",
"Column": 2,
"Line": 15
},
{
"Citation": "Psa 32:7.5",
"Current": "תִּ֫צְּרֵ֥נִי",
"Recommended": "תִּצְּ֫רֵ֥נִי",
"Note": "There is a faded Ole above Tsadi.",
"Folio": "371A",
"Column": 2,
"Line": 23
},
{
"Citation": "Psa 33:12.9",
"Current": "לֽוֹ",
"Recommended": "לוֹ",
"Note": "There is no Silluq/(Meteg under Lamed).",
"Folio": "371B",
"Column": 1,
"Line": 15
},
{
"Citation": "Psa 35:26.9",
"Current": "הַֽמַּגְדִּילִ֥ים",
"Note": "The marking under Dalet appears to be a Sheva.  [No recommended string since only a note is recommended.]",
"Folio": "372A",
"Column": 2,
"Line": 8
},
{
"Citation": "Psa 36:9.1",
"Current": "יִ֭רְוְיֻן",
"Recommended": "יִ֭רְוִיֻן",
"Note": "There appears to be a Hiriq under Vav … the blemish could possibly be a faded lower dot of a Sheva. [Perhaps just add a note rather than making a change.]",
"Folio": "372A",
"Column": 2,
"Line": 22
},
{
"Citation": "Psa 37:31.6",
  
"Current": "אֲשֻׁרָיו",
"Recommended": "אֲשֻׁרֲיו",
"Note": "There appears to be a Hataf Patah under Resh.",
"Folio": "372B",
"Column": 2,
"Line": 10
},
{
"Citation": "Psa 37:40.3",
  
"Current": "וַֽיְפַ֫לְּטֵ֥ם",
"Recommended": "וַֽיְפַלְּ֫טֵ֥ם",
"Note": "There is a blemish under Vav and the Ole is over Lamed.",
"Folio": "372B",
"Column": 2,
"Line": 21
},
{
"Citation": "Psa 38:15.8",
  
"Current": "תּוֹכָחֽוֹת",
"Recommended": "תּוֹכָֽחוֹת",
"Note": "The Meteg appears to be under the Kaf.",
"Folio": "373A",
"Column": 1,
"Line": 14
},
{
"Citation": "Psa 38:19.5",
  
"Current": "מֵֽחַטָּאתִֽי",
"Recommended": "מֵ֖חַטָּאתִֽי",
"Note": "There is a Tarcha under Mem.",
"Folio": "373A",
"Column": 1,
"Line": 18
},
{
"Citation": "Psa 39:7.7",
"Current": "יֶהֱמָי֑וּן",
"Recommended": "יֶהֱמָ֑יוּן",
"Note": "The Etnahta appears to be under Mem.",
"Folio": "373A",
"Column": 2,
"Line": 6
},
{
"Citation": "Psa 39:8.3",
"Current": "קִּוִּ֣יתִי",
"Recommended": "קִוִּ֣יתִי",
"Note": "There appears to be a speck in the upper corner of Qof ... it may be a faint Dagesh. [Perhaps just add a note rather than making a change.]",
"Folio": "373A",
"Column": 2,
"Line": 7
},
{
"Citation": "Psa 39:13.9",
"Current": "תֶּ֫חֱרַ֥שׁ",
"Recommended": "תֶּחֱ֫רַ֥שׁ",
"Note": "There is an Ole above Het.",
"Folio": "373A",
"Column": 2,
"Line": 14
},
{
"Citation": "Psa 42:9.5",
"Current": "וּ֭בַלַּיְלָה",
"Recommended": "וּ֖בַלַּיְלָה",
"Note": "There is a Tarcha under Vav. The Aleppo has a Dechi as noted in the image.",
"Folio": "374A",
"Column": 1,
"Line": 4
},
{
"Citation": "Psa 44:4.2",
"Current": "לֹ֪א",
"Recommended": "לֹ֤א",
"Note": "There is a Mahapakh under Lamed.",
"Folio": "374A",
"Column": 2,
"Line": 1
},
{
"Citation": "Psa 46:6.2",
"Current": "בְּ֭קִרְבָּהּ",
"Recommended": "בְּ֭קִרְבָּה",
"Note": "There is no Dagesh in He.",
"Folio": "374B",
"Column": 2,
"Line": 10
},
{
"Citation": "Psa 50:23.3",
"Current": "יְֽכַ֫בְּדָ֥נְנִי",
"Recommended": "יְֽכַבְּ֫דָ֥נְנִי",
"Note": "There is an Ole over Bet.",
"Folio": "375B",
"Column": 2,
"Line": 2
},
{
"Citation": "Psa 52:11.5",
"Current": "וַאֲקַוֶּ֖ה",
"Recommended": "וַאֲקַוֶּ֥ה",
"Note": "There is most likely a Merkha under the second Vav. The blemish under Patah could be mistaken as a Qamats.",
"Folio": "376A",
"Column": 1,
"Line": 15
},
{
"Citation": "Psa 53:6.2",
"Current": "פָּֽחֲדוּ־",
"Recommended": "פָּ֥חֲדוּ",
"Note": "There is no Maqaf at the end of the word but a mark resembling a Geresh. There is also most likely a Merhka under Pe.",
"Folio": "376A",
"Column": 1,
"Line": 24
},
{
"Citation": "Psa 53:6.5",
"Current": "הָ֢יָה֫",
"Recommended": "הָ֢יָ֫ה",
"Note": "There is an Ole over the Yod.",
"Folio": "376A",
"Column": 1,
"Line": 25
},
{
"Citation": "Psa 55:24.8",
"Current": "וּ֭מִרְמָה",
"Recommended": "וּ֖מִרְמָה",
"Note": "There appears to be a Tarcha under Vav. The Aleppo has a Dechi as noted in the image.",
"Folio": "376B",
"Column": 1,
"Line": 18
},
{
"Citation": "Psa 57:9.3",
"Current": "ע֭וּרָֽה",
"Recommended": "ע֭וּרָ֥ה",
"Note": "There is a Merkha under Resh.",
"Folio": "376B",
"Column": 1,
"Line": 25
},
{
"Citation": "Psa 59:2.4",
"Current": "מִּמִתְקוֹמְמַ֥י",
"Recommended": "מִּֽמִתְקוֹמְמַ֥י",
"Note": "There is a Meteg under the first Mem.",
"Folio": "377A",
"Column": 1,
"Line": 20
},
{
"Citation": "Psa 61:8.2",
"Current": "ע֭וֹלָם",
"Recommended": "ע֖וֹלָם",
"Note": "There appears to be a Tarcha under Ayin. The Aleppo has a Dechi as noted in the image.",
"Folio": "377B",
"Column": 1,
"Line": 20
},
{
"Citation": "Psa 62:4.3",
"Current": "תְּהֽוֹתְת֣וּ",
"Recommended": "תְּה֥וֹתְת֣וּ",
"Note": "There is most likely a Merkha under Hey.",
"Folio": "377B",
"Column": 2,
"Line": null
},
{
"Citation": "Psa 62:4.11",
"Current": "הַדְּחוּיָֽה",
"Recommended": "הַדְּחוּֽיָה",
"Note": "The Meteg looks like it is under Shuruk.",
"Folio": "377B",
"Column": 2,
"Line": 2
},
{
"Citation": "Psa 62:5.3",
"Current": "יָעֲצ֣וּ",
"Recommended": "יָ֥עֲצ֣וּ",
"Note": "There is a Merkha under Yod beside the Qamats.",
"Folio": "377B",
"Column": 2,
"Line": 3
},
{
"Citation": "Psa 66:2.6",
  
"Current": "תְּהִלָּתֽוֹ",
"Recommended": "תְּהִלָּֽתוֹ",
"Note": "The Meteg is under the Lamed.",
"Folio": "378A",
"Column": 2,
"Line": 17
},
{
"Citation": "Psa 66:7.7",
"Current": "הַסּוֹרְרִ֓ים",
"Recommended": "הַסוֹרְרִ֓ים",
"Note": "There is no Dagesh in Samekh.",
"Folio": "378A",
"Column": 2,
"Line": 24
},
{
"Citation": "Psa 67:2.4",
"Current": "יָ֤אֵ֥ר",
"Recommended": "יָ֤אֵ֥־ר",
"Note": "There appears to be a Maqaf in between Alef and Resh.",
"Folio": "378B",
"Column": 1,
"Line": 15
},
{
"Citation": "Psa 69:9.1",
"Current": "מ֭וּזָר",
"Recommended": "מ֖וּזָר",
"Note": "There appears to be a Tarcha under Mem ... the Aleppo reads with a Dehi as noted in the image.",
"Folio": "379A",
"Column": 2,
"Line": 11
},
{
"Citation": "Psa 69:33.7",
"Current": "לְבַבְכֶֽם",
"Note": "The mark to the left of Segol is illegible. It appears to be a smudged Meteg. [No recommended string since only a note is recommended.]",
"Folio": "379B",
"Column": 1,
"Line": 16
},
{
"Citation": "Psa 71:11.5",
"Current": "וְ֝תִפְשׂ֗וּהוּ",
"Recommended": "וְ֝תִפְשֻׂ֗וּהוּ",
"Note": "There is a Qubuts under Shin as well as a Shuruk.",
"Folio": "379B",
"Column": 2,
"Line": 17
},
{
"Citation": "Psa 71:16.4",
"Current": "יְהוִ֑ה",
"Recommended": "יְהִ֑וה",
"Note": "The Etnahta and Hiriq appear to be under the first He.",
"Folio": "379B",
"Column": 2,
"Line": 23
},
{
"Citation": "Psa 72:14.2",
"Current": "וּ֭מֵחָמָס",
"Recommended": "וּ֖מֵחָמָס",
"Note": "There is a Tarcha under Vav ... the Aleppo reads with a Dehi as noted in the image.",
"Folio": "380A",
"Column": 1,
"Line": -1
},
{
"Citation": "Psa 74:18.3",
"Current": "א֭וֹיֵב",
"Recommended": "א֖וֹיֵב",
"Note": "There appears to be a Tarcha under Alef ... the Aleppo reads with a Dehi as noted in the image.",
"Folio": "380B",
"Column": 2,
"Line": 16
},
{
"Citation": "Psa 75:2.1",
"Current": "ה֘וֹדִ֤ינוּ",
"Recommended": "ה֘וֹדִ֤ינּוּ",
"Note": "There is a Dagesh in Nun.",
"Folio": "380B",
"Column": 2,
"Line": 25
},
{
"Citation": "Psa 75:11.7",
"Current": "צַדִּֽיק",
"Recommended": "צַדִּֽ֥יק",
"Note": "There appears to be a Merkha beside Meteg under Dalet.",
"Folio": "381A",
"Column": 1,
"Line": 13
},
{
"Citation": "Psa 78:1.8",
"Current": "לְאִמְרֵי־",
"Recommended": "לְאִמְרֵי",
"Note": "There is no Maqaf after Yod.",
"Folio": "381B",
"Column": 1,
"Line": 6
},
{
"Citation": "Psa 78:7.6",
"Current": "מַֽעַלְלֵי־",
"Recommended": "מַֽעַלְלֵי",
"Note": "There is no Maqaf after Yod.",
"Folio": "381B",
"Column": 1,
"Line": 16
},
{
"Citation": "Psa 78:13.7",
"Current": "נֵֽד׃",
"Recommended": "נֵד׃",
"Note": "There is no Meteg (Silluq) under Dalet.",
"Folio": "381B",
"Column": 1,
"Line": 25
},
{
"Citation": "Psa 78:17.2",
"Current": "ע֭וֹד",
"Recommended": "ע֖וֹד",
"Note": "There appears to be a Tarcha under Ayin. The Aleppo has a Dehi as indicated in the attached image.",
"Folio": "381B",
"Column": 2,
"Line": 3
},
{
"Citation": "Psa 78:32.2",
"Current": "זֹ֭את",
"Recommended": "זֹ֥את",
"Note": "There is most likely a Merkha under Zayin. Editions of the Aleppo also have a Merkha.",
"Folio": "381B",
"Column": 2,
"Line": 23
},
{
"Citation": "Psa 78:71.3",
"Current": "הֱ֫בִיא֥וֹ",
"Recommended": "הֱבִ֫יא֥וֹ",
"Note": "There is an Ole over the Bet.",
"Folio": "382A",
"Column": 2,
"Line": 17
},
{
"Citation": "Psa 79:5.6",
"Current": "תִּבְעַ֥ר",
"Recommended": "תִּ֭בְעַ֥ר",
"Note": "There appears to be a Dehi under Tav.",
"Folio": "382B",
"Column": 1,
"Line": 1
},
{
"Citation": "Psa 79:12.9",
  
"Current": "אֲדֹנֽ͏ָי",
"Recommended": "אֲדֹֽנָי",
"Note": "The heavily marked Meteg is under Dalet.",
"Folio": "382B",
"Column": 1,
"Line": 13
},
{
"Citation": "Psa 81:11.9",
"Current": "וַאֲמַלְאֵֽהוּ",
"Recommended": "וַאֲמַּלְאֵֽהוּ",
"Note": "There appears to be a faded Dagesh in Mem.",
"Folio": "382B",
"Column": 2,
"Line": 26
},
{
"Citation": "Psa 84:3.6",
"Current": "יְה֫וָ֥ה",
"Recommended": "יְ֫הוָ֥֫ה",
"Note": "There is an Ole above Vav and appears to be another above Yod.",
"Folio": "383A",
"Column": 2,
"Line": 16
},
{
"Citation": "Psa 87:1.2",
"Current": "קֹ֭רַח",
"Recommended": "קֹ֖רַח",
"Note": "There appears to be a Tarcha under Qof. The Aleppo has a Dechi as noted in the image.",
"Folio": "383B",
"Column": 2,
"Line": 20
},
{
"Citation": "Psa 88:4.5",
"Current": "וְחַיַּ֗י",
"Recommended": "וְ֝חַיַּ֗י",
"Note": "There is a Geresh Muqdam over Vav.",
"Folio": "384A",
"Column": 1,
"Line": 8
},
{
"Citation": "Psa 88:13.4",
"Current": "וְ֝צִדְקָתְךָ֗",
"Note": "There is a spot above Qof that could be mistaken for a Revia. [No recommended string since only a note is recommended.]",
"Folio": "384A",
"Column": 1,
"Line": 21
},
{
"Citation": "Psa 89:10.2",
"Current": "מ֭וֹשֵׁל",
"Recommended": "מ֖וֹשֵׁל",
"Note": "There appears to be a Tarcha under Mem. The Aleppo has a Dechi as noted in the image.",
"Folio": "384A",
"Column": 2,
"Line": 15
},
{
"Citation": "Psa 89:9.8",
"Current": "וֶ֝אֱמֽוּנָתְךָ֗",
"Recommended": "וֶ֝אֱמ֥וּנָתְךָ֗",
"Note": "There appears to be a Merkha under Mem.",
"Folio": "384A",
"Column": 2,
"Line": 15
},
{
"Citation": "Psa 89:20.3",
"Current": "בְחָ֡זוֹן",
"Recommended": "בְחָז֡וֹן",
"Note": "There is a Pazer over Zayin.",
"Folio": "384B",
"Column": 1,
"Line": 2
},
{
"Citation": "Psa 89:42.7",
"Current": "לִשְׁכֵנֽ͏ָיו",
"Recommended": "לִשְׁכֵֽנָיו",
"Note": "There is a Meteg under Kaf.",
"Folio": "384B",
"Column": 2,
"Line": 1
},
{
"Citation": "Psa 97:11.1",
"Current": "א֭וֹר",
"Recommended": "א֖וֹר",
"Note": "There is a Tarcha under Alef. The Aleppo has a Dehi as indicated in the image.",
"Folio": "386A",
"Column": 1,
"Line": 24
},
{
"Citation": "Psa 98:9.1",
"Current": "לִֽפְֽנֵי־",
"Note": "There is possibly a Merkha under Lamed. The Aleppo reads with Merkha as noted in the image. [No recommended string since only a note is recommended.]",
"Folio": "386A",
"Column": 2,
"Line": 12
},
{
"Citation": "Psa 99:6.4",
"Current": "וּ֭שְׁמוּאֵל",
"Recommended": "וּ֖שְׁמוּאֵל",
"Note": "There is a Tarcha under Vav. The Aleppo has a Dehi as indicated in the image.",
"Folio": "386A",
"Column": 2,
"Line": 22
},
{
"Citation": "Psa 100:5.9",
"Current": "אֱמוּנָתֽוֹ",
"Recommended": "אֱמוּנָֽתוֹ",
"Note": "The Meteg appears to be under Nun.",
"Folio": "386B",
"Column": 1,
"Line": 9
},
{
"Citation": "Psa 103:2.1",
"Current": "בָּרֲכִ֣י",
"Recommended": "בָּרְכִ֣י",
"Note": "There is a Sheva under Resh.",
"Folio": "387A",
"Column": 1,
"Line": 10
},
{
"Citation": "Psa 103:14.2",
"Current": "ה֖וּא",
"Recommended": "ה֭וּא",
"Note": "There appears to be a Dehi under He. The Aleppo also has a Dehi as indicated in the image.",
"Folio": "387A",
"Column": 1,
"Line": 24
},
{
"Citation": "Psa 103:17.5",
"Current": "ע֭וֹלָם",
"Recommended": "ע֖וֹלָם",
"Note": "There is a Tarcha under Ayin. The Aleppo has a Dehi as indicated in the image.",
"Folio": "387A",
"Column": 2,
"Line": 1
},
{
"Citation": "Psa 104:1.9",
"Current": "ה֭וֹד",
"Recommended": "ה֖וֹד",
"Note": "There is a Tarcha under He with a blemish to the right. The Aleppo also has a Tarcha and indicated in the image.",
"Folio": "387A",
"Column": 2,
"Line": 11
},
{
"Citation": "Psa 104:6.6",
"Current": "יַֽעַמְדוּ־",
"Recommended": "יַ֖עַמְדוּ־",
"Note": "There is a Tarcha under Yod.",
"Folio": "387A",
"Column": 2,
"Line": 17
},
{
"Citation": "Psa 104:29.9",
"Current": "יְשׁוּבֽוּן׃",
"Recommended": "יְשׁוּֽב֥וּן׃",
"Note": "There appears to be a Merkha under Bet and a Meteg under the first Shuruk.",
"Folio": "387B",
"Column": 1,
"Line": 22
},
{
"Citation": "Psa 106:26.1",
"Current": "וַיִּשָּׂ֣א",
"Recommended": "וַיִשָּׂ֣א",
"Note": "There is no Dagesh in Yod.",
"Folio": "388B",
"Column": 1,
"Line": 3
},
{
"Citation": "Psa 106:39.4",
"Current": "בְּמַֽעַלְלֵיהֶֽם",
"Recommended": "בְּמַ֥עַלְלֵיהֶֽם",
"Note": "There is a Merkha under Mem.",
"Folio": "388B",
"Column": 1,
"Line": 19
},
{
"Citation": "Psa 106:48.1",
"Current": "בָּר֤וּךְ־",
"Recommended": "בָּ֤רֽוּךְ־",
"Note": "There is a Mahapakh appears to be under Bet and a Meteg under Resh.",
"Folio": "388B",
"Column": 2,
"Line": 2
},
{
"Citation": "Psa 107:17.4",
"Current": "וּֽ֝מֵעֲוֺֽנֹתֵיהֶ֗ם",
"Recommended": "וּֽ֝מֵעֲוֺ֥נֹתֵיהֶ֗ם",
"Note": "There is a Merkha under Vav.",
"Folio": "388B",
"Column": 2,
"Line": 23
},
{
"Citation": "Psa 108:8.4",
"Current": "אֶעְלֹ֥זָה",
"Recommended": "אֶ֫עְלֹ֥זָה",
"Note": "There is an Ole over Alef ... the Sheva under Ayin could be mistaken as a Meteg.",
"Folio": "389A",
"Column": 2,
"Line": 11
},
{
"Citation": "Psa 109:7.4",
"Current": "וּ֝תְפִלָּת֗וֹ",
"Recommended": "ו֝תְפִלָּת֗וֹ",
"Note": "There is no Shuruq dot in Vav.",
"Folio": "389B",
"Column": 1,
"Line": 2
},
{
"Citation": "Psa 109:26.4",
"Current": "ה֭וֹשִׁיעֵ֣נִי",
"Recommended": "ה֖וֹשִׁיעֵ֣נִי",
"Note": "There is a Tarcha under Hey.",
"Folio": "389B",
"Column": 1,
"Line": 26
},
{
"Citation": "Psa 112:2.2",
"Current": "דּ֭וֹר",
"Recommended": "דּ֖וֹר",
"Note": "There is a Tarcha under Dalet.",
"Folio": "390A",
"Column": 1,
"Line": 6
},
{
"Citation": "Psa 115:3.3",
"Current": "כֹּ֭ל",
"Recommended": "כֹּ֖ל",
"Note": "There appears to be a Tarcha under Kaf. The Aleppo also has a Tarcha as indicated by the image.",
"Folio": "390A",
"Column": 2,
"Line": 13
},
{
"Citation": "Psa 115:8.4",
"Current": "כֹּ֭ל",
"Recommended": "כֹּ֖ל",
"Note": "There is a Tarcha under Kaf. The Aleppo also has a Tarcha as indicated by the image.",
"Folio": "390A",
"Column": 2,
"Line": 19
},
{
"Citation": "Psa 118:27.3",
"Current": "וַיָּ֢אֶר",
"Recommended": "וַיָּ֢אֶ֫ר",
"Note": "There is an Ole above Alef.",
"Folio": "391A",
"Column": 1,
"Line": 1
},
{
"Citation": "Psa 119:16.3",
"Current": "לֹ֭א",
"Recommended": "לֹ֖א",
"Note": "There is a Tarcha under Lamed. The Aleppo also has a Tarcha as indicated by the image.",
"Folio": "391A",
"Column": 1,
"Line": 19
},
{
"Citation": "Psa 119:41.4",
"Current": "תְּ֝שֽׁוּעָתְךָ֗",
"Recommended": "תְּ֝שׁ֥וּעָתְךָ֗",
"Note": "There appears to be a Metheg that was changed to a Merkha under Shin.",
"Folio": "391A",
"Column": 2,
"Line": 20
},
{
"Citation": "Psa 119:96.1",
"Current": "לְֽכָל",
"Recommended": "לְֽכָל־",
"Note": "There is a Maqaf at the end of the word.",
"Folio": "392A",
"Column": 1,
"Line": 3
},
{
"Citation": "Psa 119:104.4",
"Current": "כֵּ֝֗ן",
"Recommended": "כֵּ֝ן",
"Note": "This most likely was a Revia Mugrash where the Revia was removed over Kaf.",
"Folio": "392A",
"Column": 1,
"Line": 11
},
{
"Citation": "Psa 119:174.4",
"Current": "וְ֝תֽוֹרָתְךָ֗",
"Recommended": "וְ֝ת֥וֹרָתְךָ֗",
"Note": "There appears to be a Merkha under the first Tav.",
"Folio": "392B",
"Column": 2,
"Line": 9
},
{
"Citation": "Psa 119:175.5",
"Current": "יַעֲזְרֻֽנִי",
"Note": "There is odd marking along both sides of the Nun. [No recommended string since only a note is recommended.]",
"Folio": "392B",
"Column": 2,
"Line": 10
},
{
"Citation": "Psa 119:176.7",
"Current": "מִ֝צְוֺתֶ֗יךָ",
"Recommended": "מִ֝צְוֺתֶיךָ֗",
"Note": "There is a Revia over the Final Kaf.",
"Folio": "392B",
"Column": 2,
"Line": 10
},
{
"Citation": "Psa 125:3.1",
"Current": "כִּ֤י",
"Recommended": "כִּ֤י׀",
"Note": "There is a Paseq after Yod.",
"Folio": "393A",
"Column": 2,
"Line": 13
},
{
"Citation": "Psa 125:3.3",
"Current": "יָנ֡וּחַ",
"Recommended": "יָנ֟וּחַ",
"Note": "It is questionable, but there appears to be a Great Pazer over Nun. The Aleppo has a Pazer and the marking is distinct. Ginsburg indicated at least two MSS he collated read with a Great Pazer.",
"Folio": "393A",
"Column": 2,
"Line": 13
},
{
"Citation": "Psa 125:3.12",
"Current": "הַצַּדִּיקִ֨ים",
"Recommended": "הַצַדִּיקִ֨ים",
"Note": "There is no Dagesh in Tsadi.",
"Folio": "393A",
"Column": 2,
"Line": 14
},
{
"Citation": "Psa 128:5.4",
"Current": "וּ֭רְאֵה",
"Recommended": "וּ֖רְאֵה",
"Note": "There appears to be a Tarcha under Vav. The Aleppo has a Dechi as indicated by the image.",
"Folio": "393B",
"Column": 1,
"Line": 16
},
{
"Citation": "Psa 129:5.2",
"Current": "וְיִסֹּ֣גוּ",
"Note": "The Dagesh is easy to miss as it is blended in the left side of the Samekh.  [No recommended string since only a note is recommended.]",
"Folio": "393B",
"Column": 1,
"Line": 23
},
{
"Citation": "Psa 133:3.3",
"Current": "שֶׁיֹּרֵד֮",
"Recommended": "שֶּׁיֹּרֵד֮",
"Note": "There is a Dagesh in Shin.",
"Folio": "394A",
"Column": 2,
"Line": 16
},
{
"Citation": "Psa 134:1.2",
"Current": "הַֽמַּ֫עֲל֥וֹת",
"Recommended": "הַֽמַּעֲ֫ל֥וֹת",
"Note": "There is an Ole above Ayin.",
"Folio": "394A",
"Column": 1,
"Line": 18
},
{
"Citation": "Psa 135:9.3",
"Current": "וּ֭מֹפְתִים",
"Recommended": "וּ֖מֹפְתִים",
"Note": "There is a Tarcha under Vav. The Aleppo also has a Tarcha as indicated in the image.",
"Folio": "394A",
"Column": 2,
"Line": 7
},
{
"Citation": "Psa 137:6.1",
"Current": "תִּדְבַּ֥ק־",
"Recommended": "תִּדְבַּֽק־",
"Note": "There is probably a Metheg (the mark is not diagonal) under Bet.",
"Folio": "394B",
"Column": 2,
"Line": 4
},
{
"Citation": "Psa 137:6.1",
"Current": "אֶ֫זְכְּרֵ֥כִי",
"Recommended": "אֶזְכְּ֫רֵ֥כִי",
"Note": "There is an Ole above the first Kaf.",
"Folio": "394B",
"Column": 2,
"Line": 4
},
{
"Citation": "Psa 137:7.11",
"Current": "עַ֝֗ד",
"Recommended": "עָ֝֗ד",
"Note": "There is a Qamats under Ayin.",
"Folio": "394B",
"Column": 2,
"Line": 7
},
{
"Citation": "Psa 138:5.4",
"Current": "כִּ֥י",
"Recommended": "כִּֽי־",
"Note": "There is a Meteg under Kaf and a Maqaf at the end of the word.",
"Folio": "394B",
"Column": 2,
"Line": 17
},
{
"Citation": "Psa 138:7.8",
"Current": "אֹ֭יְבַי",
"Recommended": "אֹ֖יְבַי",
"Note": "There is a Tarcha under Alef. The Aleppo has a Dehi as indicated in the image.",
"Folio": "394B",
"Column": 2,
"Line": 20
},
{
"Citation": "Psa 140:4.3",
"Current": "כְּֽמוֹ־",
"Recommended": "כְּֽמוֹ",
"Note": "There is no Maqaf at the end of the word.",
"Folio": "395A",
"Column": 2,
"Line": 2
},
{
"Citation": "Psa 140:11.7",
"Current": "בַּֽל־",
"Recommended": "בָּל־",
"Note": "There is a Qamats under Bet with no Meteg.",
"Folio": "395A",
"Column": 2,
"Line": 13
},
{
"Citation": "Psa 141:5.12",
"Current": "וּ֝תְפִלָּתִ֗י",
"Recommended": "ו֝תְפִלָּתִ֗י",
"Note": "There is no Shuruq dot in Vav.",
"Folio": "395A",
"Column": 2,
"Line": 26
},
{
"Citation": "Psa 145:21.3",
"Current": "יְֽדַבֶּ֫ר־",
"Recommended": "יְֽדַבֶּ֫ר",
"Note": "There is no Maqaf at the end of word.",
"Folio": "396A",
"Column": 2,
"Line": 5
},
{
"Citation": "Psa 148:5.6",
"Current": "ה֭וּא",
"Recommended": "ה֖וּא",
"Note": "There is a Tarcha under He. The Aleppo also has a Tarch as indicated by the image.",
"Folio": "396B",
"Column": 1,
"Line": 25
},
{
"Citation": "Psa 149:1.1",
"Current": "הַ֥לְלוּ יָ֨הּ",
"Recommended": "הַ֥לְלוּיָ֨הּ",
"Note": "This [word and the word after it appear to be joined, i.e. appear] to be one word. There is no space between Shuruk and Yod.",
"Folio": "396B",
"Column": 2,
"Line": 9
},
{
"Citation": "Psa 150:1.1",
"Current": "הַ֥לְלוּ יָ֨הּ",
"Recommended": "הַ֥לְלוּיָ֨הּ",
"Note": "This [word and the word after it appear to be joined, i.e. appear] to be one word. There is no space between Shuruk and Yod.",
"Folio": "396B",
"Column": 2,
"Line": 20
}
]
